redpackets/__init__.py
redpackets/compat.py
redpackets/main.py
redpackets-1.1.0.dist-info/DESCRIPTION.rst
redpackets-1.1.0.dist-info/METADATA
redpackets-1.1.0.dist-info/RECORD
redpackets-1.1.0.dist-info/WHEEL
redpackets-1.1.0.dist-info/metadata.json
redpackets-1.1.0.dist-info/top_level.txt
